sts/__init__.py
sts/sts.py
qcloud_python_sts-3.0.5.dist-info/METADATA
qcloud_python_sts-3.0.5.dist-info/WHEEL
qcloud_python_sts-3.0.5.dist-info/top_level.txt
qcloud_python_sts-3.0.5.dist-info/RECORD
